runtime/__init__.py
runtime/config.py
runtime/package.py
runtime/utils.py
enterprise_platform_runtime-0.0.2.dist-info/METADATA
enterprise_platform_runtime-0.0.2.dist-info/WHEEL
enterprise_platform_runtime-0.0.2.dist-info/top_level.txt
enterprise_platform_runtime-0.0.2.dist-info/RECORD
